{
  "user_id": "5f4f8595fe9a79ac593ba2042d596b27",
  "nickname": "Аньчи",
  "experience": 23046000,
  "rank_id": 90,
  "is_transparent": true,
  "clan_id": 377169,
  "clan_name": "Дефаинтс",
  "kill": 72522,
  "friendly_kills": 233,
  "kills": 72289,
  "death": 84429,
  "pvp": 0.86,
  "pve_kill": 116429,
  "pve_friendly_kills": 177,
  "pve_kills": 116252,
  "pve_death": 3623,
  "pve": 32.09,
  "playtime": 60917421,
  "playtime_h": 1692,
  "playtime_m": 9,
  "favoritPVP": "Medic",
  "favoritPVE": "Rifleman",
  "pve_wins": 608,
  "pvp_wins": 3987,
  "pvp_lost": 4277,
  "pve_lost": 519,
  "pve_all": 1127,
  "pvp_all": 8264,
  "pvpwl": 0.93
}